operate_excel/__init__.py
operate_excel/operate_excel.py
operate_excel-0.1.1.dist-info/METADATA
operate_excel-0.1.1.dist-info/WHEEL
operate_excel-0.1.1.dist-info/license
operate_excel-0.1.1.dist-info/top_level.txt
operate_excel-0.1.1.dist-info/RECORD
