Metadata-Version: 2.1
Name: operate-excel
Version: 0.1.1
Summary: Excel operation method
Home-page: https://github.com/ChristianYangTao/opetate_excel.git
Author: Tao Yang
Author-email: 1724805202@qq.com
License: MIT
Platform: all
Classifier: Programming Language :: Python :: 3
Classifier: License :: OSI Approved :: MIT License
Classifier: Operating System :: OS Independent
